svc_ttk/__init__.py
svc_ttk/example.py
svc_ttk/py.typed
svc_ttk/svc.tcl
svc_ttk/theme/dark.tcl
svc_ttk/theme/light.tcl
svc_ttk/theme/sprites_dark.tcl
svc_ttk/theme/sprites_light.tcl
svc_ttk/theme/spritesheet_dark.png
svc_ttk/theme/spritesheet_light.png
svc_ttk-2.6.4.dist-info/METADATA
svc_ttk-2.6.4.dist-info/WHEEL
svc_ttk-2.6.4.dist-info/top_level.txt
svc_ttk-2.6.4.dist-info/RECORD
