Metadata-Version: 2.2
Name: svc_ttk
Version: 2.6.4
Summary: A modified theme of Sun-Valley-ttk with crimson hinting
Home-page: https://github.com/initiateit/Sun-Valley-ttk-crimson-theme
Author-email: initiateit <jason@initiateit.com.au>, rdbende <rdbende@proton.me>
License: MIT
Project-URL: Homepage, https://github.com/initiateit/Sun-Valley-ttk-crimson-theme
Project-URL: Documentation, https://github.com/initiateit/Sun-Valley-ttk-crimson-theme
Project-URL: Tracker, https://github.com/initiateit/Sun-Valley-ttk-crimson-theme/issues
Keywords: svc-ttk,crimson,red,tcl,tcl/tk,theme,tile,tk,ttk,tkinter,modern,fluent,dark-theme,sun-valley,windows-11,winui
Classifier: Intended Audience :: Developers
Classifier: Topic :: Software Development :: User Interfaces
Classifier: Programming Language :: Python :: 3 :: Only
Classifier: Programming Language :: Python :: 3.8
Classifier: Programming Language :: Python :: 3.9
Classifier: Programming Language :: Python :: 3.10
Classifier: Programming Language :: Python :: 3.11
Classifier: Programming Language :: Python :: 3.12
Classifier: Programming Language :: Tcl
Classifier: License :: OSI Approved :: MIT License
Classifier: Operating System :: OS Independent
Requires-Python: >=3.8
Provides-Extra: test
Requires-Dist: pytest; extra == "test"
Requires-Dist: mypy; extra == "test"
Dynamic: home-page
Dynamic: requires-python
